bc_jsonpath_ng/__init__.py
bc_jsonpath_ng/__version__.py
bc_jsonpath_ng/exceptions.py
bc_jsonpath_ng/jsonpath.py
bc_jsonpath_ng/lexer.py
bc_jsonpath_ng/parser.py
bc_jsonpath_ng/py.typed
bc_jsonpath_ng/bin/__init__.py
bc_jsonpath_ng/bin/jsonpath.py
bc_jsonpath_ng/ext/__init__.py
bc_jsonpath_ng/ext/arithmetic.py
bc_jsonpath_ng/ext/filter.py
bc_jsonpath_ng/ext/iterable.py
bc_jsonpath_ng/ext/parser.py
bc_jsonpath_ng/ext/string.py
bc_jsonpath_ng-1.5.9.dist-info/LICENSE
bc_jsonpath_ng-1.5.9.dist-info/METADATA
bc_jsonpath_ng-1.5.9.dist-info/WHEEL
bc_jsonpath_ng-1.5.9.dist-info/entry_points.txt
bc_jsonpath_ng-1.5.9.dist-info/top_level.txt
bc_jsonpath_ng-1.5.9.dist-info/RECORD
